LICENSE
MANIFEST.in
README.rst
setup.py
upload.bat
radware_octavia_rocky_driver/__init__.py
radware_octavia_rocky_driver/config.py
radware_octavia_rocky_driver/dm_utils.py
radware_octavia_rocky_driver/feedback.py
radware_octavia_rocky_driver/monitoring.py
radware_octavia_rocky_driver/octavia_provider_driver.py
radware_octavia_rocky_driver/radware_provider_exceptions.py
radware_octavia_rocky_driver/vdirect_adc_wf_driver.py
radware_octavia_rocky_driver/vdirect_client.py
radware_octavia_rocky_driver.egg-info/PKG-INFO
radware_octavia_rocky_driver.egg-info/SOURCES.txt
radware_octavia_rocky_driver.egg-info/dependency_links.txt
radware_octavia_rocky_driver.egg-info/entry_points.txt
radware_octavia_rocky_driver.egg-info/not-zip-safe
radware_octavia_rocky_driver.egg-info/top_level.txt