Metadata-Version: 1.1
Name: radware-octavia-rocky-driver
Version: 4.6.0.post1
Summary: Octavia Radware driver for Openstack Rocky
Home-page: https://pypi.python.org/pypi/radware_octavia_rocky_driver
Author: Evgeny Fedoruk, Radware
Author-email: evgenyf@radware.com
License: UNKNOWN
Keywords: radware,vdirect,lbaas,ADC,octavia
Platform: UNKNOWN
Classifier: Environment :: OpenStack
Classifier: Intended Audience :: Information Technology
Classifier: Intended Audience :: System Administrators
Classifier: License :: OSI Approved :: Apache Software License
Classifier: Operating System :: POSIX :: Linux
Classifier: Programming Language :: Python :: 2.7
